ministring.cp313-win_amd64.pyd
py_ministring-0.1.1.dist-info/licenses/LICENCE
py_ministring-0.1.1.dist-info/METADATA
py_ministring-0.1.1.dist-info/WHEEL
py_ministring-0.1.1.dist-info/top_level.txt
py_ministring-0.1.1.dist-info/RECORD
