Metadata-Version: 2.4
Name: py-ministring
Version: 0.1.1
Summary: Experimental compact UTF-8 string type for CPython
Author-email: AI-Stratov <workistratov@gmail.com>
License: MIT
Project-URL: Homepage, https://github.com/AI-Stratov/py-ministring
Project-URL: Repository, https://github.com/AI-Stratov/py-ministring.git
Project-URL: Issues, https://github.com/AI-Stratov/py-ministring/issues
Keywords: string,utf8,unicode,c-extension,performance
Classifier: Development Status :: 3 - Alpha
Classifier: Intended Audience :: Developers
Classifier: Programming Language :: Python :: 3
Classifier: Programming Language :: Python :: 3.8
Classifier: Programming Language :: Python :: 3.9
Classifier: Programming Language :: Python :: 3.10
Classifier: Programming Language :: Python :: 3.11
Classifier: Programming Language :: Python :: 3.12
Classifier: Programming Language :: Python :: 3.13
Classifier: Programming Language :: C
Classifier: Topic :: Software Development :: Libraries :: Python Modules
Classifier: Topic :: Text Processing :: General
Requires-Python: >=3.8
License-File: LICENCE
Provides-Extra: test
Requires-Dist: pytest>=6.0; extra == "test"
Provides-Extra: dev
Requires-Dist: pytest>=6.0; extra == "dev"
Requires-Dist: build; extra == "dev"
Requires-Dist: twine; extra == "dev"
Dynamic: license-file
